airtouch2/at2/At2Aircon.py
airtouch2/at2/At2Client.py
airtouch2/at2/At2Group.py
airtouch2/at2/__init__.py
airtouch2/at2plus/At2PlusAircon.py
airtouch2/at2plus/At2PlusClient.py
airtouch2/at2plus/At2PlusGroup.py
airtouch2/at2plus/__init__.py
airtouch2/common/Buffer.py
airtouch2/common/NetClient.py
airtouch2/common/__init__.py
airtouch2/common/interfaces.py
airtouch2/helpers/__init__.py
airtouch2/helpers/diff_bytes.py
airtouch2/protocol/__init__.py
airtouch2/protocol/at2/__init__.py
airtouch2/protocol/at2/constants.py
airtouch2/protocol/at2/conversions.py
airtouch2/protocol/at2/enums.py
airtouch2/protocol/at2/lookups.py
airtouch2/protocol/at2/message_common.py
airtouch2/protocol/at2/messages/RequestState.py
airtouch2/protocol/at2/messages/SystemInfo.py
airtouch2/protocol/at2/messages/__init__.py
airtouch2/protocol/at2/messages/ac_commands.py
airtouch2/protocol/at2/messages/group_commands.py
airtouch2/protocol/at2plus/constants.py
airtouch2/protocol/at2plus/control_status_common.py
airtouch2/protocol/at2plus/conversions.py
airtouch2/protocol/at2plus/crc16_modbus.py
airtouch2/protocol/at2plus/enums.py
airtouch2/protocol/at2plus/extended_common.py
airtouch2/protocol/at2plus/message_common.py
airtouch2/protocol/at2plus/messages/AcAbilityMessage.py
airtouch2/protocol/at2plus/messages/AcControl.py
airtouch2/protocol/at2plus/messages/AcStatus.py
airtouch2/protocol/at2plus/messages/GroupControl.py
airtouch2/protocol/at2plus/messages/GroupNames.py
airtouch2/protocol/at2plus/messages/GroupStatus.py
airtouch2-0.8.6.dist-info/LICENSE
airtouch2-0.8.6.dist-info/METADATA
airtouch2-0.8.6.dist-info/WHEEL
airtouch2-0.8.6.dist-info/top_level.txt
airtouch2-0.8.6.dist-info/RECORD
