Metadata-Version: 2.1
Name: airtouch2
Version: 0.8.6
Summary: API for the monitoring and control of a Polyaire Airtouch 2 system over the local network
Author-email: Nathan Van der Hoek <nathanmvdh@gmail.com>
License: MIT License
Project-URL: Homepage, https://github.com/nathanvdh/airtouch2-python
Keywords: air,conditioner,automation
Classifier: Programming Language :: Python :: 3
Classifier: License :: OSI Approved :: MIT License
Classifier: Operating System :: OS Independent
Classifier: Development Status :: 3 - Alpha
Classifier: Intended Audience :: Developers
Classifier: Topic :: Home Automation
Classifier: Topic :: Software Development :: Embedded Systems
Requires-Python: >=3.10
License-File: LICENSE
